tree_adapter.py
fs_tree_spec-0.2.0.dist-info/METADATA
fs_tree_spec-0.2.0.dist-info/WHEEL
fs_tree_spec-0.2.0.dist-info/entry_points.txt
fs_tree_spec-0.2.0.dist-info/licenses/LICENSE
fs_tree_spec-0.2.0.dist-info/RECORD
