Metadata-Version: 2.4
Name: fs-tree-spec
Version: 0.2.0
Summary: Translate between ASCII 'tree' text, JSON/YAML tree specs, and real directory structures.
Project-URL: Homepage, https://github.com/swoodeng/fs-tree-spec
Project-URL: Source, https://github.com/swoodeng/fs-tree-spec
Project-URL: Issues, https://github.com/swoodeng/fs-tree-spec/issues
Project-URL: PyPI, https://pypi.org/project/fs-tree-spec/
Author: Stephen Wood
License: MIT
License-File: LICENSE
Keywords: cli,directory,filesystem,json,tool,tree,yaml
Requires-Python: >=3.11
Provides-Extra: test
Requires-Dist: pytest; extra == 'test'
Provides-Extra: yaml
Requires-Dist: pyyaml>=6.0; extra == 'yaml'
